pyampute/__init__.py
pyampute/ampute.py
pyampute/utils.py
pyampute/exploration/__init__.py
pyampute/exploration/mcar_statistical_tests.py
pyampute/exploration/md_patterns.py
pyampute-0.0.3.dist-info/LICENSE.md
pyampute-0.0.3.dist-info/METADATA
pyampute-0.0.3.dist-info/WHEEL
pyampute-0.0.3.dist-info/top_level.txt
pyampute-0.0.3.dist-info/RECORD
