Metadata-Version: 2.1
Name: pyampute
Version: 0.0.3
Summary: Transformer for generating multivariate missingness in complete datasets
Home-page: UNKNOWN
Author: Rianne Schouten,Davina Zamanzadeh,Prabhant Singh
Author-email: r.m.schouten@tue.nl,davzaman@gmail.com,p.singh@tue.nl
License: BSD
Project-URL: Documentation, https://rianneschouten.github.io/pyampute/build/html/index.html
Project-URL: Source Code, https://github.com/RianneSchouten/pyampute
Platform: UNKNOWN
Provides-Extra: docs
License-File: LICENSE.md
